window_tracker_x11/__init__.py
window_tracker_x11/__main__.py
window_tracker_x11/__version__.py
window_tracker_x11/track.py
window_tracker_x11-0.0.12.data/data/lib/systemd/user/window-tracker-x11.service
window_tracker_x11-0.0.12.data/data/lib/window_tracker_x11/config.py.sample
window_tracker_x11-0.0.12.dist-info/DESCRIPTION.rst
window_tracker_x11-0.0.12.dist-info/METADATA
window_tracker_x11-0.0.12.dist-info/RECORD
window_tracker_x11-0.0.12.dist-info/WHEEL
window_tracker_x11-0.0.12.dist-info/entry_points.txt
window_tracker_x11-0.0.12.dist-info/metadata.json
window_tracker_x11-0.0.12.dist-info/top_level.txt
