Metadata-Version: 2.0
Name: window-tracker-x11
Version: 0.0.12
Summary: Track and log what windows/apps you use when working with X11
Home-page: https://github.com/hrehfeld/window-tracker-x11
Author: Hauke Rehfeld
Author-email: windowtrackerx11@haukerehfeld.de
License: AGPLv3
Platform: UNKNOWN
Classifier: License :: OSI Approved :: GNU Affero General Public License v3 or later (AGPLv3+)
Classifier: Programming Language :: Python
Classifier: Programming Language :: Python :: 3
Classifier: Programming Language :: Python :: 3.3
Classifier: Programming Language :: Python :: 3.4
Classifier: Programming Language :: Python :: 3.5
Classifier: Programming Language :: Python :: 3.6
Classifier: Programming Language :: Python :: Implementation :: CPython
Classifier: Programming Language :: Python :: Implementation :: PyPy
Requires-Dist: python-xlib
